eeyore_nlp/__init__.py
eeyore_nlp/extractions/__init__.py
eeyore_nlp/extractions/relationship_extracts.py
eeyore_nlp/extractions/scope_overlap_extract.py
eeyore_nlp/extractions/tag_extract.py
eeyore_nlp/generators/__init__.py
eeyore_nlp/generators/alias.py
eeyore_nlp/generators/markov_chain.py
eeyore_nlp/integrations/__init__.py
eeyore_nlp/integrations/spacy_integrations.py
eeyore_nlp/models/__init__.py
eeyore_nlp/models/context.py
eeyore_nlp/models/kb_triple.py
eeyore_nlp/models/phrases.py
eeyore_nlp/models/relationships.py
eeyore_nlp/models/scope.py
eeyore_nlp/models/tag.py
eeyore_nlp/networks/__init__.py
eeyore_nlp/networks/graph.py
eeyore_nlp/networks/kb.py
eeyore_nlp/pipelines/__init__.py
eeyore_nlp/pipelines/abs.py
eeyore_nlp/pipelines/context_factory.py
eeyore_nlp/pipelines/context_pipeline.py
eeyore_nlp/pipelines/context_pipes.py
eeyore_nlp/pipelines/pipe_wrappers.py
eeyore_nlp/pipelines/text_pipeline.py
eeyore_nlp/pipelines/text_pipes.py
eeyore_nlp/pipelines/tokenizers.py
eeyore_nlp/pumps/__init__.py
eeyore_nlp/pumps/abs.py
eeyore_nlp/pumps/context_pumps.py
eeyore_nlp/pumps/text_pumps.py
eeyore_nlp/rulesets/__init__.py
eeyore_nlp/rulesets/collection.py
eeyore_nlp/rulesets/loader.py
eeyore_nlp/taggers/__init__.py
eeyore_nlp/taggers/abs.py
eeyore_nlp/taggers/chunkers.py
eeyore_nlp/taggers/mappers.py
eeyore_nlp/taggers/scopers.py
eeyore_nlp/utils/__init__.py
eeyore_nlp/utils/iob2.py
eeyore_nlp/utils/merger.py
eeyore_nlp/utils/relationships.py
eeyore_nlp/utils/spell_checker.py
eeyore_nlp-0.0.12.dist-info/LICENSE
eeyore_nlp-0.0.12.dist-info/METADATA
eeyore_nlp-0.0.12.dist-info/WHEEL
eeyore_nlp-0.0.12.dist-info/top_level.txt
eeyore_nlp-0.0.12.dist-info/RECORD
