Metadata-Version: 2.1
Name: eeyore-nlp
Version: 0.0.12
Summary: UNKNOWN
Home-page: UNKNOWN
License: UNKNOWN
Platform: UNKNOWN
Requires-Dist: pylint (==2.7.4)
Requires-Dist: pytest (==6.2.1)
Requires-Dist: pycodestyle (==2.7.0)
Requires-Dist: networkx (==2.5)
Requires-Dist: nltk (==3.5)
Requires-Dist: numpy (==1.19.5)
Requires-Dist: spacy (==3.0.6)
Requires-Dist: beautifulsoup4 (==4.9.3)
